utils.py
build/lib/utils.py
build/lib/coevolution/__init__.py
build/lib/coevolution/champions.py
build/lib/ocamlec_plt/__init__.py
build/lib/ocamlec_plt/utils.py
build/lib/ocamlec_plt/coevolution/__init__.py
build/lib/ocamlec_plt/coevolution/champions.py
build/lib/tests/test.py
coevolution/__init__.py
coevolution/champions.py
ocamlec_plt/__init__.py
ocamlec_plt/utils.py
ocamlec_plt/coevolution/__init__.py
ocamlec_plt/coevolution/champions.py
ocamlec_plt/coevolution/costatistics.py
ocamlec_plt/tests/test.py
tests/test.py
ocamlec_plt-0.0.6.dist-info/METADATA
ocamlec_plt-0.0.6.dist-info/WHEEL
ocamlec_plt-0.0.6.dist-info/top_level.txt
ocamlec_plt-0.0.6.dist-info/RECORD
